datahub_classify/__init__.py
datahub_classify/constants.py
datahub_classify/helper_classes.py
datahub_classify/infotype_helper.py
datahub_classify/infotype_predictor.py
datahub_classify/infotype_utils.py
datahub_classify/reference_input.py
acryl_datahub_classify-0.0.11.dist-info/METADATA
acryl_datahub_classify-0.0.11.dist-info/WHEEL
acryl_datahub_classify-0.0.11.dist-info/top_level.txt
acryl_datahub_classify-0.0.11.dist-info/RECORD
